odoo9_addon_crm_claim_rma-9.0.1.0.0.99.dev15-py2.7-nspkg.pth
odoo9_addon_crm_claim_rma-9.0.1.0.0.99.dev15.dist-info/METADATA
odoo9_addon_crm_claim_rma-9.0.1.0.0.99.dev15.dist-info/RECORD
odoo9_addon_crm_claim_rma-9.0.1.0.0.99.dev15.dist-info/WHEEL
odoo9_addon_crm_claim_rma-9.0.1.0.0.99.dev15.dist-info/namespace_packages.txt
odoo9_addon_crm_claim_rma-9.0.1.0.0.99.dev15.dist-info/top_level.txt
odoo_addons/crm_claim_rma/README.rst
odoo_addons/crm_claim_rma/__init__.py
odoo_addons/crm_claim_rma/__openerp__.py
odoo_addons/crm_claim_rma/data/crm_claim_category.xml
odoo_addons/crm_claim_rma/data/crm_team.xml
odoo_addons/crm_claim_rma/data/ir_sequence_type.xml
odoo_addons/crm_claim_rma/i18n/crm_claim_rma.pot
odoo_addons/crm_claim_rma/i18n/de.po
odoo_addons/crm_claim_rma/i18n/es.po
odoo_addons/crm_claim_rma/i18n/es_MX.po
odoo_addons/crm_claim_rma/i18n/es_PA.po
odoo_addons/crm_claim_rma/i18n/es_VE.po
odoo_addons/crm_claim_rma/i18n/fr.po
odoo_addons/crm_claim_rma/i18n/pt_BR.po
odoo_addons/crm_claim_rma/i18n/ro.po
odoo_addons/crm_claim_rma/i18n/sl.po
odoo_addons/crm_claim_rma/models/__init__.py
odoo_addons/crm_claim_rma/models/account_invoice.py
odoo_addons/crm_claim_rma/models/account_invoice_line.py
odoo_addons/crm_claim_rma/models/claim_line.py
odoo_addons/crm_claim_rma/models/crm_claim.py
odoo_addons/crm_claim_rma/models/invoice_no_date.py
odoo_addons/crm_claim_rma/models/procurement_group.py
odoo_addons/crm_claim_rma/models/product_no_supplier.py
odoo_addons/crm_claim_rma/models/stock_move.py
odoo_addons/crm_claim_rma/models/stock_picking.py
odoo_addons/crm_claim_rma/models/substate_substate.py
odoo_addons/crm_claim_rma/security/ir.model.access.csv
odoo_addons/crm_claim_rma/static/description/icon.png
odoo_addons/crm_claim_rma/test/test_invoice_refund.yml
odoo_addons/crm_claim_rma/tests/__init__.py
odoo_addons/crm_claim_rma/tests/test_claim.py
odoo_addons/crm_claim_rma/tests/test_picking_creation.py
odoo_addons/crm_claim_rma/views/account_invoice.xml
odoo_addons/crm_claim_rma/views/claim_line.xml
odoo_addons/crm_claim_rma/views/crm_claim.xml
odoo_addons/crm_claim_rma/views/res_partner.xml
odoo_addons/crm_claim_rma/views/stock_view.xml
odoo_addons/crm_claim_rma/wizards/__init__.py
odoo_addons/crm_claim_rma/wizards/account_invoice_refund.py
