Metadata-Version: 2.1
Name: odoo9-addon-crm-claim-rma
Version: 9.0.1.0.0.99.dev15
Summary: RMA Claim (Product Return Management)
Home-page: https://odoo-community.org
Author: Akretion, Camptocamp, Eezee-it, MONK Software, Vauxoo, Odoo Community Association (OCA)
Author-email: support@odoo-community.org
License: AGPL-3
Platform: UNKNOWN
Classifier: Programming Language :: Python
Classifier: Framework :: Odoo
Classifier: License :: OSI Approved :: GNU Affero General Public License v3
Requires-Python: ~=2.7
Requires-Dist: odoo9-addon-crm-claim-rma-code
Requires-Dist: odoo9-addon-crm-rma-location
Requires-Dist: odoo9-addon-product-warranty
Requires-Dist: odoo (<9.1a,>=9.0a)
